package/__init__.py
package/scrap.py
package/section.py
scrapper/__init__.py
scrapper/scrap.py
scrapper/section.py
wiki_scrapper-0.8.dist-info/METADATA
wiki_scrapper-0.8.dist-info/WHEEL
wiki_scrapper-0.8.dist-info/top_level.txt
wiki_scrapper-0.8.dist-info/RECORD
