Metadata-Version: 2.1
Name: wiki-scrapper
Version: 0.8
Summary: UNKNOWN
Home-page: https://github.com/Krishap-s/wiki_scraper
Author: Krishap S
Author-email: krishapsreenivasn.s2020@vitstudent.ac.in
License: UNKNOWN
Platform: UNKNOWN
Requires-Dist: beautifulsoup4 (==4.9.3)
Requires-Dist: bs4 (==0.0.1)
Requires-Dist: certifi (==2020.12.5)
Requires-Dist: chardet (==4.0.0)
Requires-Dist: idna (==2.10)
Requires-Dist: requests (==2.25.1)
Requires-Dist: soupsieve (==2.1)
Requires-Dist: urllib3 (==1.26.2)
